{"cron_job_id": 2, "cron_expression": "*/15 * * * *", "edge_function_name": "vendor-shopify-inventory", "cron_job_name": "vendor-shopify-inventory_invoke", "raw_sql": "\n            CREATE OR REPLACE PROCEDURE vendor_shopify_inventory_ce403cdc()\n            LANGUAGE plpgsql\n            AS $$\n            BEGIN\n            PERFORM net.http_post(\n            url:='https://gvcswimqaxvylgxbklbz.supabase.co/functions/v1/vendor-shopify-inventory',\n            headers:=jsonb_build_object('Content-Type', 'application/json'),\n            body:='{\"edge_function_name\":\"vendor-shopify-inventory\"}',\n            timeout_milliseconds:=10000\n            );\n            COMMIT;\n            END;\n            $$;\n\n            SELECT cron.schedule('vendor-shopify-inventory_invoke', '*/15 * * * *', 'CALL vendor_shopify_inventory_ce403cdc()');\n            "}